<?xml version="1.0" encoding="utf-8" ?>
<dwsync>
<file name="arc-current-electric.png" server="linux243.unoeuro.com" local="131886442691446696" remote="131895922200000000" Dst="1" />
<file name="beach_weather.png" server="linux243.unoeuro.com" local="131888272266108397" remote="131895922200000000" Dst="1" />
<file name="brainstorm_sweetbot.png" server="linux243.unoeuro.com" local="131890833326145866" remote="131895922200000000" Dst="1" />
<file name="cardsort_eksamensprojekt_sem1.png" server="linux243.unoeuro.com" local="131889097365384257" remote="131895922200000000" Dst="1" />
<file name="fb_icon.png" server="linux243.unoeuro.com" local="131891704263471167" remote="131895922200000000" Dst="1" />
<file name="dream_your_portfolio_original.png" server="linux243.unoeuro.com" local="131886416989512859" remote="131895922200000000" Dst="1" />
<file name="dark_sphere_moon.png" server="linux243.unoeuro.com" local="131886454781394746" remote="131895922200000000" Dst="1" />
<file name="fb_icon_eksamensproject_1sem.png" server="linux243.unoeuro.com" local="131891700157958784" remote="131895922200000000" Dst="1" />
<file name="flow-chart_eksamensprojekt_sem1.png" server="linux243.unoeuro.com" local="131889943154152437" remote="131895922200000000" Dst="1" />
<file name="flow_chart_sweetbot_eksamensproject_sem1.png" server="linux243.unoeuro.com" local="131890830637903847" remote="131895922200000000" Dst="1" />
<file name="final_wireframe_sweetbot_eksamensproject_sem1.png" server="linux243.unoeuro.com" local="131890831401750955" remote="131895922200000000" Dst="1" />
<file name="flow_background.png" server="linux243.unoeuro.com" local="131886444396760795" remote="131895922200000000" Dst="1" />
<file name="gruppe_billede_sweetbot.png" server="linux243.unoeuro.com" local="131892487544959478" remote="131895922200000000" Dst="1" />
<file name="grid_structure_final_build_eksamensprojekt_1sem.png" server="linux243.unoeuro.com" local="131894321053903010" remote="131895922200000000" Dst="1" />
<file name="icons_original_portfolio.png" server="linux243.unoeuro.com" local="131886463404114281" remote="131895922200000000" Dst="1" />
<file name="intro_projekt_titel_billede.png" server="linux243.unoeuro.com" local="131888292537522823" remote="131895922800000000" Dst="1" />
<file name="linkedin_icon_eksamensprojekt_1sem.png" server="linux243.unoeuro.com" local="131891700967541873" remote="131895922800000000" Dst="1" />
<file name="kortsortering_sweetbot.png" server="linux243.unoeuro.com" local="131890838368396220" remote="131895922800000000" Dst="1" />
<file name="mercedes.png" server="linux243.unoeuro.com" local="131891611065613698" remote="131895922800000000" Dst="1" />
<file name="map_eksamensprojekt_1sem.PNG" server="linux243.unoeuro.com" local="131891671022880017" remote="131895922800000000" Dst="1" />
<file name="grid_structure_final_build_eksamensprojekt_1sem.JPG" server="linux243.unoeuro.com" local="131894318061793280" remote="131895922800000000" Dst="1" />
<file name="me_myself_andi.png" server="linux243.unoeuro.com" local="131886436755061883" remote="131895922800000000" Dst="1" />
<file name="moodboard_eksamensprojekt_sem1.png" server="linux243.unoeuro.com" local="131886412199630755" remote="131895922800000000" Dst="1" />
<file name="new_fonts_eksamensprojekt_sem1.png" server="linux243.unoeuro.com" local="131890792533360603" remote="131895922800000000" Dst="1" />
<file name="me_myself_andi_resized.png" server="linux243.unoeuro.com" local="131891561693529559" remote="131895922800000000" Dst="1" />
<file name="moodboard_persona_sweetbot.png" server="linux243.unoeuro.com" local="131890835258703760" remote="131895922800000000" Dst="1" />
<file name="pbs-missionstatement_eksamensprojekt_sem1.png" server="linux243.unoeuro.com" local="131889942409749405" remote="131895922800000000" Dst="1" />
<file name="pbs_struktur_sweetbot.png" server="linux243.unoeuro.com" local="131890835757246066" remote="131895922800000000" Dst="1" />
<file name="preliminary_card_sort_eksamensprojekt_semester1.png" server="linux243.unoeuro.com" local="131889096954894256" remote="131895922800000000" Dst="1" />
<file name="peru_dancing.png" server="linux243.unoeuro.com" local="131891577563560386" remote="131895922800000000" Dst="1" />
<file name="Sitemap_eksamens_project_1sem.png" server="linux243.unoeuro.com" local="131889942750733779" remote="131895922800000000" Dst="1" />
<file name="sitemap_sweetbot.png" server="linux243.unoeuro.com" local="131890833868868978" remote="131895922800000000" Dst="1" />
<file name="styletile_sweetbot.png" server="linux243.unoeuro.com" local="131890831761924838" remote="131895922800000000" Dst="1" />
<file name="styletile_final_build_eksamensprojekt_1sem.png" server="linux243.unoeuro.com" local="131894320622990830" remote="131895922800000000" Dst="1" />
<file name="sweetbot_branding_final_design.png" server="linux243.unoeuro.com" local="131890880559787680" remote="131895922800000000" Dst="1" />
<file name="sweetbot_branding_final_design_ex2.png" server="linux243.unoeuro.com" local="131890880821493362" remote="131895922800000000" Dst="1" />
<file name="sweetbot_compare.png" server="linux243.unoeuro.com" local="131890882832054912" remote="131895922800000000" Dst="1" />
<file name="sweetbot_compare_2.png" server="linux243.unoeuro.com" local="131890883794503732" remote="131895922800000000" Dst="1" />
<file name="sweetbot_branding_original_ex2.png" server="linux243.unoeuro.com" local="131890880768089458" remote="131895922800000000" Dst="1" />
<file name="sweetbot_compare_3.png" server="linux243.unoeuro.com" local="131890884731428279" remote="131895922800000000" Dst="1" />
<file name="sweetbot_icons.png" server="linux243.unoeuro.com" local="131890875140357921" remote="131895922800000000" Dst="1" />
<file name="sweetbot_om_os_final_design.png" server="linux243.unoeuro.com" local="131886432963886634" remote="131895922800000000" Dst="1" />
<file name="sweetbot_index_final_design.png" server="linux243.unoeuro.com" local="131890880972448968" remote="131895922800000000" Dst="1" />
<file name="sweetbot_om_os_original.png" server="linux243.unoeuro.com" local="131886433968335309" remote="131895922800000000" Dst="1" />
<file name="styletile_final_build_eksamensprojekt_1sem.JPG" server="linux243.unoeuro.com" local="131894318414993963" remote="131895922800000000" Dst="1" />
<file name="sweetbot_original_branding_page.png" server="linux243.unoeuro.com" local="131890880422615634" remote="131895922800000000" Dst="1" />
<file name="trello_eksamens_projekt_sem1.png" server="linux243.unoeuro.com" local="131889941848019928" remote="131895922800000000" Dst="1" />
<file name="sweetbot_original_design_index.png" server="linux243.unoeuro.com" local="131890881034641233" remote="131895922800000000" Dst="1" />
<file name="twitter_icon_eksamensprojekt_1sem.png" server="linux243.unoeuro.com" local="131891701852300714" remote="131895922800000000" Dst="1" />
<file name="wbs_eksamensprojekt_sem1.png" server="linux243.unoeuro.com" local="131889941332826209" remote="131895922800000000" Dst="1" />
<file name="wbs_sweetbot.png" server="linux243.unoeuro.com" local="131890829792933945" remote="131895922800000000" Dst="1" />
<file name="wireframe-sitemap.png" server="linux243.unoeuro.com" local="131886436146671096" remote="131895922800000000" Dst="1" />
<file name="wireframe_fuldskaerm2_eksamensprojekt_sem.png" server="linux243.unoeuro.com" local="131889090550787176" remote="131895922800000000" Dst="1" />
<file name="wireframe_mobil_eksamensprojekt_sem.png" server="linux243.unoeuro.com" local="131889091717794429" remote="131895922800000000" Dst="1" />
</dwsync>